{
  "version": "6",
  "dialect": "sqlite",
  "id": "aa34974c-2749-4442-a373-708ecce0aae8",
  "prevId": "d41f49a1-bdbc-493c-9111-bb83b6176c3b",
  "tables": {
    "settings": {
      "name": "settings",
      "columns": {
        "key": {
          "name": "key",
          "type": "text",
          "primaryKey": true,
          "notNull": true,
          "autoincrement": false
        },
        "value": {
          "name": "value",
          "type": "integer",
          "primaryKey": false,
          "notNull": true,
          "autoincrement": false
        }
      },
      "indexes": {},
      "foreignKeys": {},
      "compositePrimaryKeys": {},
      "uniqueConstraints": {},
      "checkConstraints": {}
    },
    "weight": {
      "name": "weight",
      "columns": {
        "date": {
          "name": "date",
          "type": "text",
          "primaryKey": true,
          "notNull": true,
          "autoincrement": false
        },
        "weight": {
          "name": "weight",
          "type": "real",
          "primaryKey": false,
          "notNull": false,
          "autoincrement": false
        },
        "unit": {
          "name": "unit",
          "type": "integer",
          "primaryKey": false,
          "notNull": false,
          "autoincrement": false,
          "default": 0
        }
      },
      "indexes": {},
      "foreignKeys": {},
      "compositePrimaryKeys": {},
      "uniqueConstraints": {},
      "checkConstraints": {}
    }
  },
  "views": {},
  "enums": {},
  "_meta": {
    "schemas": {},
    "tables": {},
    "columns": {}
  },
  "internal": {
    "indexes": {}
  }
}